rtst/__init__.py
rtst/main.py
rtst/recognizers.py
rtst-0.1.4.6.dist-info/License.md
rtst-0.1.4.6.dist-info/METADATA
rtst-0.1.4.6.dist-info/WHEEL
rtst-0.1.4.6.dist-info/entry_points.txt
rtst-0.1.4.6.dist-info/top_level.txt
rtst-0.1.4.6.dist-info/RECORD
