Metadata-Version: 2.1
Name: rtst
Version: 0.1.4.6
License-File: License.md
Requires-Dist: speechrecognition
Requires-Dist: langdetect
Requires-Dist: googletrans
Requires-Dist: pyttsx3
Requires-Dist: azure-cognitiveservices-speech
Requires-Dist: boto3
Requires-Dist: transformers
Requires-Dist: numpy
Requires-Dist: tensorflow
Requires-Dist: soundfile
Requires-Dist: librosa
Requires-Dist: PyAudio
